setup.py
vqsr_cnn/__init__.py
vqsr_cnn/inference.py
vqsr_cnn.egg-info/PKG-INFO
vqsr_cnn.egg-info/SOURCES.txt
vqsr_cnn.egg-info/dependency_links.txt
vqsr_cnn.egg-info/not-zip-safe
vqsr_cnn.egg-info/top_level.txt