Metadata-Version: 1.0
Name: vqsr-cnn
Version: 0.0.11
Summary: Variant quality score recalibration with Convolutional Neural Networks
Home-page: https://github.com/broadinstitute/dsde-deep-learning
Author: Sam Friedman
Author-email: sam@broadinstitute.org
License: MIT
Platform: UNKNOWN
